TeleCryptoBot/__init__.py
TeleCryptoBot/app_stats.py
TeleCryptoBot/balance.py
TeleCryptoBot/base.py
TeleCryptoBot/check.py
TeleCryptoBot/currencies.py
TeleCryptoBot/exchange.py
TeleCryptoBot/invoice.py
TeleCryptoBot/negr.py
TeleCryptoBot/profile.py
TeleCryptoBot/rates.py
TeleCryptoBot/request.py
TeleCryptoBot/test.py
TeleCryptoBot/transfer.py
TeleCryptoBot-1.3.dist-info/METADATA
TeleCryptoBot-1.3.dist-info/WHEEL
TeleCryptoBot-1.3.dist-info/top_level.txt
TeleCryptoBot-1.3.dist-info/RECORD
